{
  "version": "1.0",
  "name": "SFP+HDMI20+OUT+CAB",
  "id": "imagine-sfphdmi20outcab",
  "orderCode": null,
  "orderNumber": "SFP+HDMI20+OUT+CAB",
  "moduleFormFactorId": "sfp",
  "manufacturerId": "imagine",
  "portTypes": [
    {
      "name": "",
      "direction": "OUT",
      "connectorId": "HDMI_D_f",
      "compatibleSignalTypes": [
        "HDMI_10",
        "HDMI_11",
        "HDMI_12",
        "HDMI_12A",
        "HDMI_14",
        "HDMI_14A",
        "HDMI_14B",
        "HDMI_20"
      ]
    }
  ]
}
